{
    "backend": "api-server-flask",
    "db_name": "",
    "db_pass": "",
    "db_type": "sqlite",
    "db_user": "",
    "dbms": "1",
    "description": "generated product",
    "design": "soft-ui-dashboard",
    "docker": "1",
    "err_code": 0,
    "frontend": "react",
    "heroku": "0",
    "pattern": "fullstack",
    "pro": "0",
    "task_id": "6ef96289-9af8-4df5-b18c-6160f21ea2e4",
    "task_info": "Upload Sources [0%] - 283 files",
    "task_output": "6ef96289-9af8-4df5-b18c-6160f21ea2e4.zip",
    "task_result": "SUCCESS",
    "task_state": "RUNNING",
    "task_ts_end": "2024-02-19-18-31-27",
    "task_ts_start": "2024-02-19-18-31-25"
}